incuna_pigeon-0.1.0.dist-info/top_level.txt
incuna_pigeon-0.1.0.dist-info/DESCRIPTION.rst
incuna_pigeon-0.1.0.dist-info/RECORD
incuna_pigeon-0.1.0.dist-info/metadata.json
incuna_pigeon-0.1.0.dist-info/METADATA
incuna_pigeon-0.1.0.dist-info/WHEEL
tests/__init__.py
tests/test_notification.py
pigeon/__init__.py
pigeon/notification.py
