Metadata-Version: 1.1
Name: incuna-pigeon
Version: 0.1.0
Summary: Notification management
Home-page: https://github.com/incuna/incuna-pigeon
Author: Incuna
Author-email: admin@incuna.com
License: BSD
Keywords: notifications
Platform: UNKNOWN
Classifier: Development Status :: 3 - Alpha
Classifier: Intended Audience :: Developers
Classifier: Topic :: Communications
Classifier: License :: OSI Approved :: BSD License
Classifier: Programming Language :: Python :: 3
Classifier: Programming Language :: Python :: 3 :: Only
Classifier: Programming Language :: Python :: 3.4
